{
  "$ref": "#/definitions/docs",
  "definitions": {
    "docs": {
      "type": "object",
      "properties": {
        "title": {
          "type": "string"
        },
        "description": {
          "type": "string"
        },
        "editUrl": {
          "anyOf": [
            {
              "type": "string",
              "format": "uri"
            },
            {
              "type": "boolean"
            }
          ],
          "default": true
        },
        "template": {
          "type": "string",
          "enum": [
            "doc",
            "splash"
          ],
          "default": "doc"
        },
        "hero": {},
        "lastUpdated": {
          "anyOf": [
            {
              "anyOf": [
                {
                  "type": "string",
                  "format": "date-time"
                },
                {
                  "type": "string",
                  "format": "date"
                },
                {
                  "type": "integer",
                  "format": "unix-time"
                }
              ]
            },
            {
              "type": "boolean"
            }
          ]
        },
        "prev": {},
        "next": {},
        "banner": {
          "type": "object",
          "properties": {
            "content": {
              "type": "string"
            }
          },
          "required": [
            "content"
          ],
          "additionalProperties": false
        },
        "pagefind": {
          "type": "boolean",
          "default": true
        },
        "draft": {
          "type": "boolean",
          "default": false
        },
        "tableOfContents": {},
        "head": {
          "type": "array",
          "default": []
        },
        "sidebar": {
          "type": "object",
          "properties": {
            "order": {
              "type": "number"
            },
            "label": {
              "type": "string"
            },
            "hidden": {
              "type": "boolean",
              "default": false
            },
            "badge": {},
            "attrs": {
              "type": "object",
              "additionalProperties": {},
              "default": {}
            }
          },
          "additionalProperties": false,
          "default": {}
        },
        "$schema": {
          "type": "string"
        }
      },
      "required": [
        "title"
      ],
      "additionalProperties": true
    }
  },
  "$schema": "http://json-schema.org/draft-07/schema#"
}